pelican/plugins/pelican_cite2/__init__.py
pelican/plugins/pelican_cite2/templates/citations.html
pelican/plugins/pelican_cite2/templates/label.html
pelican_cite2-1.1.5.dist-info/LICENSE
pelican_cite2-1.1.5.dist-info/METADATA
pelican_cite2-1.1.5.dist-info/WHEEL
pelican_cite2-1.1.5.dist-info/RECORD
