Metadata-Version: 2.3
Name: pelican-cite2
Version: 1.1.5
Summary: Allows the use of BibTeX citations within a Pelican site
License: AGPL-3.0
Keywords: pelican,plugin
Author: Johan Vergeer
Author-email: johanvergeer@gmail.com
Requires-Python: >=3.8,<4.0
Classifier: Development Status :: 5 - Production/Stable
Classifier: Environment :: Console
Classifier: Framework :: Pelican
Classifier: Framework :: Pelican :: Plugins
Classifier: Intended Audience :: End Users/Desktop
Classifier: License :: OSI Approved :: GNU Affero General Public License v3
Classifier: Operating System :: OS Independent
Classifier: Programming Language :: Python :: 3
Classifier: Programming Language :: Python :: 3.8
Classifier: Programming Language :: Python :: 3.9
Classifier: Programming Language :: Python :: 3.10
Classifier: Programming Language :: Python :: 3.11
Classifier: Programming Language :: Python :: 3.12
Classifier: Programming Language :: Python :: 3.13
Classifier: Topic :: Internet :: WWW/HTTP
Classifier: Topic :: Software Development :: Libraries :: Python Modules
Provides-Extra: markdown
Requires-Dist: docutils (!=0.21.post1)
Requires-Dist: jinja2 (>=3.1.2,<4.0.0)
Requires-Dist: markdown (>=3.1.1,<4.0.0) ; extra == "markdown"
Requires-Dist: pelican (>=4.2,<5.0)
Requires-Dist: pybtex (>=0.25.1,<0.26.0)
Project-URL: Documentation, https://docs.getpelican.com/
Project-URL: Funding, https://donate.getpelican.com/
Project-URL: Repository, https://github.com/efcy/pelican-cite
Project-URL: Source, https://github.com/johanvergeer/pelican-cite
Project-URL: Tracker, https://github.com/johanvergeer/pelican-cite/issues
